Blauwal3_Network-1.9.0-py3.10-nspkg.pth
orangecontrib/network/__init__.py
orangecontrib/network/i18n_config.py
orangecontrib/network/locale/network.de.yml
orangecontrib/network/locale/network.en.yml
orangecontrib/network/locale/network.zh.yml
orangecontrib/network/network/__init__.py
orangecontrib/network/network/base.py
orangecontrib/network/network/community.py
orangecontrib/network/network/embeddings.py
orangecontrib/network/network/generate.py
orangecontrib/network/network/readwrite.py
orangecontrib/network/network/twomode.py
orangecontrib/network/network/layout/__init__.py
orangecontrib/network/network/layout/_fr_layout.c
orangecontrib/network/network/layout/_fr_layout.cp310-win_amd64.pyd
orangecontrib/network/network/layout/_fr_layout.cpython-38-darwin.so
orangecontrib/network/network/layout/_fr_layout.pyx
orangecontrib/network/networks/airtraffic.net
orangecontrib/network/networks/airtraffic_items.tab
orangecontrib/network/networks/davis.net
orangecontrib/network/networks/davis.tsv
orangecontrib/network/networks/dicty_publication.net
orangecontrib/network/networks/dicty_publication_edges.tab
orangecontrib/network/networks/dicty_publication_items.tab
orangecontrib/network/networks/lastfm.net
orangecontrib/network/networks/lastfm.tab
orangecontrib/network/networks/lastfm_all.tab
orangecontrib/network/networks/lastfm_tags.tab
orangecontrib/network/networks/leu_by_genesets.net
orangecontrib/network/networks/leu_by_genesets_items.tab
orangecontrib/network/networks/leu_by_pmid.net
orangecontrib/network/networks/leu_by_pmid_items.tab
orangecontrib/network/networks/leu_huttenhower_a.net
orangecontrib/network/networks/leu_huttenhower_a_items.tab
orangecontrib/network/networks/makeNetworkList.py
orangecontrib/network/networks/mips_c2_cp_leu.net
orangecontrib/network/networks/mips_c2_cp_leu_items.tab
orangecontrib/network/networks/network_info.tab
orangecontrib/network/tests/__init__.py
orangecontrib/network/tests/test-arcslist.net
Blauwal3_Network-1.9.0.dist-info/COPYING
Blauwal3_Network-1.9.0.dist-info/LICENSE
Blauwal3_Network-1.9.0.dist-info/METADATA
Blauwal3_Network-1.9.0.dist-info/WHEEL
Blauwal3_Network-1.9.0.dist-info/entry_points.txt
Blauwal3_Network-1.9.0.dist-info/namespace_packages.txt
Blauwal3_Network-1.9.0.dist-info/top_level.txt
Blauwal3_Network-1.9.0.dist-info/RECORD
