Metadata-Version: 2.1
Name: Blauwal3-Network
Version: 1.9.0
Summary: 用于网络的蓝鲸数据挖掘附加组件。
Home-page: https://github.com/biolab/orange3-network
Author: 大圣实验室
Author-email: dashenglab@163.com
License: GPLv3
Keywords: network,network analysis,network layout,network visualization,data mining,machine learning,artificial intelligence,Blauwal3,Blauwal3 add-on
Classifier: Development Status :: 4 - Beta
Classifier: Environment :: X11 Applications :: Qt
Classifier: Environment :: Console
Classifier: Environment :: Plugins
Classifier: Programming Language :: Python
Classifier: License :: OSI Approved :: GNU General Public License v3 or later (GPLv3+)
Classifier: Operating System :: OS Independent
Classifier: Topic :: Scientific/Engineering :: Artificial Intelligence
Classifier: Topic :: Scientific/Engineering :: Visualization
Classifier: Topic :: Software Development :: Libraries :: Python Modules
Classifier: Intended Audience :: Education
Classifier: Intended Audience :: Science/Research
Classifier: Intended Audience :: Developers
Requires-Python: >=3.8
License-File: LICENSE
License-File: COPYING
Requires-Dist: anyqt
Requires-Dist: gensim
Requires-Dist: Blauwal3
Requires-Dist: Blauwal3-widget-base
Requires-Dist: pyqtgraph
Requires-Dist: scipy>=1.7.3
Requires-Dist: scikit-learn
Provides-Extra: gui
Requires-Dist: AnyQt; extra == "gui"
Provides-Extra: doc
Requires-Dist: sphinx; extra == "doc"
Requires-Dist: recommonmark; extra == "doc"
Requires-Dist: sphinx-rtd-theme; extra == "doc"
Provides-Extra: rest
Requires-Dist: numpydoc; extra == "rest"
Provides-Extra: test
Requires-Dist: coverage; extra == "test"
